pykagskangbolu/__init__.py
pykagskangbolu/pykagskangbolu.py
pykagskangbolu-0.1.0.dist-info/LICENSE
pykagskangbolu-0.1.0.dist-info/WHEEL
pykagskangbolu-0.1.0.dist-info/METADATA
pykagskangbolu-0.1.0.dist-info/RECORD
